{"description": "A sexy achievement file parser with real-time notification, automatic screenshot and playtime tracking.\nView every achievements earned on your PC whether it's coming from Steam, a Steam emulator, and more.", "updated": "2024-03-22T01:33:29Z", "galleryUrl": "https://community.chocolatey.org/packages/achievement-watcher/1.6.8", "abuseUrl": "https://community.chocolatey.org/package/ReportAbuse/achievement-watcher/1.6.8", "licenseUrl": "https://github.com/xan105/Achievement-Watcher/blob/master/LICENSE", "packageName": "achievement-watcher", "displayName": "Achievement Watcher", "summary": "A sexy achievement file parser with real-time notification, automatic screenshot and playtime tracking.", "version": "1.6.8", "icon": "https://rawcdn.githack.com/xan105/Achievement-Watcher/1507bc5e2fa570cc46e5a225ae0a4a282b897d5f/app/resources/icon/icon.png", "author": "xan105", "downloadCount": 215, "tags": ["steam", "notification", "uplay", "rpcs3", "trophy", "achievement", "playtime-tracking"]}