{"description": "## Adobe Creative Cloud Client Installer\nAdobe Creative Cloud Client Installer for installing creative cloud subscription applications\nRequest a user before continuing, so not fully silent\n\n### Package-specific issue\nIf this package isn't up-to-date for some days, [Create an issue](https://github.com/tunisiano187/Chocolatey-packages/issues/new/choose)\n\nSupport the package maintainer and [![Patreon](https://cdn.jsdelivr.net/gh/tunisiano187/Chocolatey-packages@d15c4e19c709e7148588d4523ffc6dd3cd3c7e5e/icons/patreon.png)](https://www.patreon.com/tunisiano)", "updated": "2022-07-24T02:15:01Z", "galleryUrl": "https://community.chocolatey.org/packages/adobe-creative-cloud/5.3.5.15", "abuseUrl": "https://community.chocolatey.org/package/ReportAbuse/adobe-creative-cloud/5.3.5.15", "licenseUrl": "http://www.adobe.com/legal/general-terms.html", "packageName": "adobe-creative-cloud", "displayName": "Adobe Creative Cloud Client", "summary": "Adobe Creative Cloud Client Installer for installing creative cloud subscription applications", "version": "5.3.5.15", "icon": "https://cdn.jsdelivr.net/gh/tunisiano187/Chocolatey-packages@a8856a907c19803f761e269fc0aca3a21cb7c9f8/icons/adobe-creative-cloud.png", "author": "Adobe", "downloadCount": 858575, "tags": ["Adobe", "Creative", "Cloud", "NotSilent"]}