{"description": "#### New package name: **[adobereader](https://chocolatey.org/packages/adobereader)**\n\n---\n\n`adobereader-update` has been deprecated because functionality to install updates has now been built directly into the `adobereader` package.\n\nThis package exists only for backward compatibility to provide a transitional dummy package for existing users and scripts which may still use this package ID.", "updated": "2024-03-24T01:03:28Z", "galleryUrl": "https://community.chocolatey.org/packages/adobereader-update/18.011.99999", "abuseUrl": "https://community.chocolatey.org/package/ReportAbuse/adobereader-update/18.011.99999", "licenseUrl": "http://www.adobe.com/products/eulas/pdfs/Reader10_combined-20100625_1419.pdf", "packageName": "adobereader-update", "displayName": "[Deprecated] Adobe Reader DC Update", "summary": "View, print, sign, and annotate PDF files", "version": "18.011.99999", "icon": "", "author": "Adobe", "downloadCount": 6284397, "tags": ["adobereader", "adobe", "acrobat", "reader", "DC", "pdf"]}