{"description": "Easily switch the default audio device, input or output, on any Windows PC (Vista and above).\n\nUsing this application you can switch output OR input sound devices at the click of a button, or the press of a key.\n\nI designed this application to be incredibly small and lightweight. There is no bloat, it does exactly what it should, nothing more, nothing less.", "updated": "2024-03-23T14:33:35Z", "galleryUrl": "https://community.chocolatey.org/packages/audioswitcher/1.8.0.142", "abuseUrl": "https://community.chocolatey.org/package/ReportAbuse/audioswitcher/1.8.0.142", "licenseUrl": "https://github.com/xenolightning/AudioSwitcher/blob/master/LICENSE", "packageName": "audioswitcher", "displayName": "Audio Switcher", "summary": "Easily Switch Default Audio Devices on Windows", "version": "1.8.0.142", "icon": "https://cdn.rawgit.com/dtgm/chocolatey-packages/ddf3e8934b6374c8806b58de6ab5995158cd1d81/icons/audioswitcher.png", "author": "Sean Chapman", "downloadCount": 5203, "tags": ["audio", "device", "manager"]}