{"description": "A multi-system emulator written in C#. As well as quality-of-life features for casual players, it also has recording/playback and debugging tools, making it the first choice for TASers (Tool-Assisted Speedrunners).", "updated": "2022-07-22T22:45:01Z", "galleryUrl": "https://community.chocolatey.org/packages/bizhawk/2.8", "abuseUrl": "https://community.chocolatey.org/package/ReportAbuse/bizhawk/2.8", "licenseUrl": "https://github.com/TASVideos/BizHawk/blob/master/LICENSE", "packageName": "bizhawk", "displayName": "BizHawk", "summary": "BizHawk is a multi-system emulator written in C#.", "version": "2.8", "icon": "", "author": "TASVideos", "downloadCount": 1287, "tags": ["c-sharp", "c-plus-plus", "winforms", "emulator", "emulation", "saturn", "dotnet", "speedrunning"]}