{"description": "---\n\n### [choco://choco-sandbox](choco://choco-sandbox)\nTo use choco:// protocol URLs, install [(unofficial) choco:// Protocol support ](https://chocolatey.org/packages/choco-protocol-support)\n\n---\n\n![Screenshot of choco-sandbox](https://raw.githubusercontent.com/bcurran3/ChocolateyPackages/master/choco-sandbox/choco-sandbox_screenshot.png)\n\t\n### WHAT IS THIS?\n**Chocolatey Sandbox** sets up a customized and customizable [Windows Sandbox](https://learn.microsoft.com/en-us/windows/security/application-security/application-isolation/windows-sandbox/windows-sandbox-overview) environment with Chocolatey installed.\n\t\n### WHO IS THIS FOR?\n**Chocolatey Sandbox** is for anyone who may want to \"test drive\" Chocolatey packages in a [sandbox](https://en.wikipedia.org/wiki/Sandbox_(computer_security)).\n\n\n### FEATURES:\n* Installs Chocolatey from the web on first run and caches it for subsequent runs of the sandbox.\n* Automatically upgrades Chocolatey to the latest version on every run.\n* Automatically sets up the default PowerShell profile with Chocolatey tab completion as well as some shortcuts (cup, cinst, cuninst, clist).\n* Automatically installs packages from packages.config if it exists.\n* Automatically runs choco-sandbox-customize.ps1 for further customization if it exists.\n\n\n---\n\n**If you find Chocolatey Sandbox useful, please consider donating:\nhttps://www.paypal.me/bcurran3donations or become a patron at https://www.patreon.com/bcurran3**\n\n---", "updated": "2024-03-20T04:03:38Z", "galleryUrl": "https://community.chocolatey.org/packages/choco-sandbox/1.0.0", "abuseUrl": "https://community.chocolatey.org/package/ReportAbuse/choco-sandbox/1.0.0", "licenseUrl": "https://wiki.creativecommons.org/wiki/Public_domain", "packageName": "choco-sandbox", "displayName": "(unofficial) Chocolatey Sandbox", "summary": "Chocolatey Sandbox runs Windows Sandbox with Chocolatey pre-installed.", "version": "1.0.0", "icon": "https://raw.githubusercontent.com/bcurran3/ChocolateyPackages/master/choco-sandbox/choco-sandbox_icon.png", "author": "bcurran3", "downloadCount": 85, "tags": ["bcurran3", "unofficial", "chocolatey", "powershell", "sandbox", "test", "environment", "packagers", "maintainers"]}