{"description": "cimer - Visual countdown timer", "updated": "2024-03-17T00:03:25Z", "galleryUrl": "https://community.chocolatey.org/packages/cimer/0.6", "abuseUrl": "https://community.chocolatey.org/package/ReportAbuse/cimer/0.6", "licenseUrl": "http://www.gnu.org/licenses/gpl.html", "packageName": "cimer", "displayName": "cimer - Visual countdown timer", "summary": "cimer", "version": "0.6", "icon": "http://code.google.com/p/cimer/logo?cct=1299526340", "author": "Jaakko Vuori,  Teppo Eeva,  Santeri Vesalainen", "downloadCount": 1226, "tags": ["cimer", "admin"]}