{"description": "Command line application for creating CSP requests, encrypting and decrypting files, signing files using public key cryptography, creating file hashes", "updated": "2024-03-17T22:48:42Z", "galleryUrl": "https://community.chocolatey.org/packages/cryptcp/5.0.10804", "abuseUrl": "https://community.chocolatey.org/package/ReportAbuse/cryptcp/5.0.10804", "licenseUrl": "https://www.cryptopro.ru/sites/default/files/products/cryptcp/licence.pdf", "packageName": "cryptcp", "displayName": "cryptcp", "summary": "Command line application for creating CSP requests, encrypting and decrypting files, signing files using public key cryptography, creating file hashes", "version": "5.0.10804", "icon": "https://www.cryptopro.ru/sites/default/files/theme321_logo.png", "author": "\u041e\u041e\u041e \"\u041a\u0420\u0418\u041f\u0422\u041e-\u041f\u0420\u041e\"", "downloadCount": 854, "tags": ["cryptopro", "crypto", "crypto-pro", "csp", "csp-request", "encryption", "signing", "hash", "hashing"]}