{"description": "[DevCon](http://msdn.microsoft.com/en-us/library/windows/hardware/ff544707) is a command-line tool that displays detailed information about devices, and lets you search for and manipulate devices from the command line. DevCon enables, disables, installs, configures, and removes devices on the local computer and displays detailed information about devices on local and remote computers. DevCon is included in the WDK.\n\nThis pacakge includes both an x86 and an x64 version of the DevCon application:\n* DevCon32.exe\n* DevCon64.exe\n\nPlease use the version applicable to your Operating System.\n\nThese files are obtained from the WDK for Windows 10 build 1607.\nThe Devcon.exe (both the 32-bit and 64-bit versions) can be found in the Windows Device Kit (WDK).\nThe WDK installer can be downloaded from [here](http://go.microsoft.com/fwlink/p/?LinkId=526733).\nFor more information on downloading the WDK and associated tools, see [this page](https://developer.microsoft.com/en-us/windows/hardware/windows-driver-kit).", "updated": "2024-03-23T09:03:44Z", "galleryUrl": "https://community.chocolatey.org/packages/devcon.portable/10.0.10586.23", "abuseUrl": "https://community.chocolatey.org/package/ReportAbuse/devcon.portable/10.0.10586.23", "licenseUrl": "https://github.com/Microsoft/Windows-driver-samples/blob/master/LICENSE", "packageName": "devcon.portable", "displayName": "DevCon (Portable)", "summary": "Device Console (DevCon) Tool (Portable)", "version": "10.0.10586.23", "icon": "", "author": "Microsoft", "downloadCount": 220833, "tags": ["DevCon", "DeviceConsole", "WDK", "WindowsDriverKit"]}