{"description": "The new Droid font collection provides an extensive set of styles, weights and language support. Each of the Droid fonts was custom designed by Ascender and optimized for on-screen legibility with the Android platform.", "updated": "2024-03-21T23:03:30Z", "galleryUrl": "https://community.chocolatey.org/packages/DroidFonts/4.0.0", "abuseUrl": "https://community.chocolatey.org/package/ReportAbuse/DroidFonts/4.0.0", "licenseUrl": "http://www.apache.org/licenses/LICENSE-2.0", "packageName": "DroidFonts", "displayName": "", "summary": "", "version": "4.0.0", "icon": "", "author": "Monotype Imaging Holdings", "downloadCount": 3138, "tags": ["font", "monospace"]}