{"description": "If you're a writer, then you need the Em and En dashes. This ultra-simple program makes it easy for you to just type the dash and move on. It does this in a variety of ways - you choose which one's you like.", "updated": "2024-03-22T21:33:45Z", "galleryUrl": "https://community.chocolatey.org/packages/em-n-en/1.0.0", "abuseUrl": "https://community.chocolatey.org/package/ReportAbuse/em-n-en/1.0.0", "licenseUrl": "", "packageName": "em-n-en", "displayName": "Em-n-En", "summary": "Em and En dash keyboard-ization \u2013(^\u2014^)\u2013", "version": "1.0.0", "icon": "https://rawcdn.githack.com/CemraJC/em-n-en/e06e5e60267e63c917dd263e978c293fdd91b85b/icon/Eminen-icon.png?raw=true", "author": "https://github.com/CemraJC/em-n-en/graphs/contributors", "downloadCount": 360, "tags": ["em-n-en"]}