{"description": "frozenbytes.essentials", "updated": "2024-03-15T20:19:25Z", "galleryUrl": "https://community.chocolatey.org/packages/frozenbytes.essentials/1.07", "abuseUrl": "https://community.chocolatey.org/package/ReportAbuse/frozenbytes.essentials/1.07", "licenseUrl": "", "packageName": "frozenbytes.essentials", "displayName": "frozenbytes.essentials", "summary": "frozenbytes.essentials", "version": "1.07", "icon": "https://raw.githubusercontent.com/segilbert/presentations/master/images/create_frozen_liquid_effects.jpg", "author": "Sean Gilbert", "downloadCount": 4659, "tags": ["frozenbytes", "frozenbytes.essentials", "utilities", "tools", "chocolatey"]}