{"description": "While it doesn't tend to fully replace traditional `find` and `ls`, **fselect** has these nice features:\n\n\t\t* SQL-like (not real SQL, but highly relaxed!) grammar easily understandable by humans\n\t\t* complex queries\n\t\t* aggregate, statistics, date, and other functions\n\t\t* search within archives\n\t\t* `.gitignore`, `.hgignore`, and `.dockerignore` support (experimental)\n\t\t* search by width and height of images, EXIF metadata\n\t\t* search by MP3 info\n\t\t* search by extended file attributes\n\t\t* search by file hashes\n\t\t* search by MIME type\n\t\t* shortcuts to common file types\n\t\t* interactive mode\n\t\t* various output formatting (CSV, JSON, and others)\n\n\t\tMore is under way! Please take a look at the documentation for the examples of usage.", "updated": "2024-03-23T23:03:35Z", "galleryUrl": "https://community.chocolatey.org/packages/fselect/0.8.5", "abuseUrl": "https://community.chocolatey.org/package/ReportAbuse/fselect/0.8.5", "licenseUrl": "https://github.com/jhspetersson/fselect/blob/master/LICENSE-MIT", "packageName": "fselect", "displayName": "fselect", "summary": "Find files with SQL-like queries", "version": "0.8.5", "icon": "", "author": "jhspetersson", "downloadCount": 3142, "tags": ["fselect", "cli", "file", "search", "find", "sql"]}