{"description": "Greenery is a cryptocurrency wallet developed by Greenfire to be the defacto Multichain \ncryptocurrency wallet for Avid traders and businesses. Greenery solves the problem of users having to \nretrieve data about their holdings from multiple sources by centralizing everything in an easy to use, \nclean and beautiful interface.\n\nGreenery allows users to manage multiple wallet addresses per currency supported, issue invoices \ndenominated in crypto and fully supports human readable address protocols of Unstoppable Domains, \nTezos Domains and Ethereum Name Service.", "updated": "2024-03-19T23:03:30Z", "galleryUrl": "https://community.chocolatey.org/packages/greenery/0.9.7", "abuseUrl": "https://community.chocolatey.org/package/ReportAbuse/greenery/0.9.7", "licenseUrl": "", "packageName": "greenery", "displayName": "Greenery", "summary": "A Cryptocurrency wallet with bookkeeping and accounting functionality for web3 and defi.", "version": "0.9.7", "icon": "https://cdn.jsdelivr.net/gh/GreenfireInc/Releases.Greenery@main/icons/128x128.png", "author": "Greenfire", "downloadCount": 237, "tags": ["accounting", "bitcoin", "blockchain", "bookkeeping", "business", "cryptocurrency", "defi", "ethereum", "finance", "invoicing", "wallet", "web3"]}