{"description": "ICQ New \u2014 stay connected\n\n![BaseWindow](https://raw.githubusercontent.com/zersh01/chocolatey-icq/master/BaseWindow.png)\n\nConvert audio messages to text, use smart replies, stay online\neven with bad internet connection\n\n![Audio2Text](https://raw.githubusercontent.com/zersh01/chocolatey-icq/master/Audio2Text.png)", "updated": "2024-03-23T04:18:51Z", "galleryUrl": "https://community.chocolatey.org/packages/icq/23.2.0.48119", "abuseUrl": "https://community.chocolatey.org/package/ReportAbuse/icq/23.2.0.48119", "licenseUrl": "https://help.mail.ru/legal/terms/icq/eng/copyright", "packageName": "icq", "displayName": "ICQ", "summary": "ICQ New", "version": "23.2.0.48119", "icon": "https://cdn.jsdelivr.net/gh/zersh01/chocolatey-icq@master/icq.png", "author": "LLC Mail.Ru", "downloadCount": 14331, "tags": ["icq", "messenger"]}