{"description": "---\n\n### [choco://intel-dsa](choco://intel-dsa)\nTo use choco:// protocol URLs, install [(unofficial) choco:// Protocol support ](https://chocolatey.org/packages/choco-protocol-support)\n\n---\n\n\n### Purpose\n\nThe Intel\u00ae Driver & Support Assistant enables you to scan computing devices for the latest drivers available from Intel. This tool has the main interface hosted on Intel\u2019s support website and provides a more integrated support experience to users. It has an enhanced detection engine to ensure that customers are given complete and accurate information and a scan frequency option to change from a \u201crun-once\u201d tool to a persistent experience that can provide customers with driver updates more quickly.\n\nProducts supported: Graphics drivers, wireless networking, Intel\u00ae NUCs, and Intel\u00ae Compute Sticks\n\n### Required to install and use utility\n\n* A broadband Internet connection is required to use this utility.\n* Operating system requirements for installation: This application installs on Windows 7*, Windows 8*, Windows 8.1*, Windows\u00ae 10, and Windows 11*.\n* We recommend performing a Windows* update to bring your operating system up to date with the latest .NET.\n* This application does not support Internet Explorer* browser. We recommend using Chrome*, Firefox*, or Edge* (version 44.17763/18.17763 or newer) browsers.\n\n**[PACKAGE NOTES](https://github.com/bcurran3/ChocolateyPackages/blob/master/intel-dsa/readme.md)**\n\n\n---\n\n**Click here to [Patreon-ize](https://www.patreon.com/bcurran3) the package maintainer.**\n\n---", "updated": "2024-03-24T01:03:28Z", "galleryUrl": "https://community.chocolatey.org/packages/intel-dsa/23.4.39.9", "abuseUrl": "https://community.chocolatey.org/package/ReportAbuse/intel-dsa/23.4.39.9", "licenseUrl": "http://www.intel.com/content/www/us/en/legal/terms-of-use.html", "packageName": "intel-dsa", "displayName": "Intel\u00ae Driver & Support Assistant (Install)", "summary": "Intel\u00ae Driver & Support Assistant enables you to scan computing devices for the latest drivers available from Intel.", "version": "23.4.39.9", "icon": "https://raw.githubusercontent.com/bcurran3/ChocolateyPackages/master/intel-dsa/intel-dsa_icon.png", "author": "Intel Corporation", "downloadCount": 1726535, "tags": ["dsa", "intel", "driver", "support", "assistant", "update", "utility"]}