{"description": "Kontur.Certificates is a tool for installing GOST root certificates for Kontur services, used for single sign on by digital signature certificate verification", "updated": "2024-03-23T09:34:34Z", "galleryUrl": "https://community.chocolatey.org/packages/kontur-certificates/4.8.30.383", "abuseUrl": "https://community.chocolatey.org/package/ReportAbuse/kontur-certificates/4.8.30.383", "licenseUrl": "https://install.kontur.ru/", "packageName": "kontur-certificates", "displayName": "Kontur.Certificates (Install)", "summary": "Kontur.Certificates is a tool for installing GOST root certificates for Kontur services", "version": "4.8.30.383", "icon": "https://kontur.ru/theme/ver-1321485457/common/images/logo_social.png", "author": "PF SKB Kontur AO", "downloadCount": 6517, "tags": ["crypto", "office", "digital-signature", "signature", "gost", "cades", "bookkeeping", "kontur", "admin"]}