{"description": "a chemically intelligent desktop toolkit built to help you draw, edit, publish, render, import and export your chemical structures and as well as allowing you to convert between various chemical and graphical file formats.", "updated": "2024-03-23T08:03:28Z", "galleryUrl": "https://community.chocolatey.org/packages/marvin/23.2.0", "abuseUrl": "https://community.chocolatey.org/package/ReportAbuse/marvin/23.2.0", "licenseUrl": "", "packageName": "marvin", "displayName": "ChemAxon Marvin Suite", "summary": "a chemically intelligent desktop toolkit built to help you draw, edit, publish, render, import and export your chemical structures and as well as allowing you to convert between various chemical and graphical file formats.", "version": "23.2.0", "icon": "", "author": "ChemAxon", "downloadCount": 138, "tags": ["chemistry", "organic-chemistry", "chemdraw", "molecule", "java"]}