{"description": "Microsoft OLE DB Driver 19 for SQL Server is a single dynamic-link library (DLL) containing run-time support for applications using native-code APIs to connect to Microsoft SQL Server 2012, SQL Server 2014, SQL Server 2016, SQL Server 2017, SQL Server 2019, SQL Server 2022, Analytics Platform System, Azure SQL Database and Azure SQL Data Warehouse. \n\nMicrosoft OLE DB Driver 19 for SQL Server should be used to create new applications or enhance existing applications that need to take advantage of newer SQL Server features. \n\nThis redistributable installer for Microsoft OLE DB Driver 19 for SQL Server installs the client components needed during run time to take advantage of newer SQL Server features, and optionally installs the header files needed to develop an application that uses the OLE DB API.", "updated": "2024-03-24T01:03:28Z", "galleryUrl": "https://community.chocolatey.org/packages/msoledbsql/19.3.2", "abuseUrl": "https://community.chocolatey.org/package/ReportAbuse/msoledbsql/19.3.2", "licenseUrl": "", "packageName": "msoledbsql", "displayName": "Microsoft OLE DB Driver for SQL Server", "summary": "The Microsoft OLE DB Driver for SQL Server provides native connectivity from Windows to Microsoft SQL Server and Microsoft Azure SQL Database.", "version": "19.3.2", "icon": "", "author": "Microsoft", "downloadCount": 223263, "tags": ["msoledbsql", "SQLServer", "Native", "OLEDB"]}