{"description": "# obs-scripts\n[![Chocolatey](https://img.shields.io/chocolatey/v/obs-studio-wiiplayer2-scripts.svg?style=flat-square)](https://chocolatey.org/packages/obs-studio-wiiplayer2-scripts)\n[![GitHub release](https://img.shields.io/github/release/wiiplayer2/obs-scripts.svg?style=flat-square)](https://github.com/WiiPlayer2/obs-scripts/releases/latest)\n[![GitHub Release Date](https://img.shields.io/github/release-date/WiiPlayer2/obs-scripts.svg?style=flat-square)](https://github.com/WiiPlayer2/obs-scripts/releases/latest)\n[![GitHub last commit](https://img.shields.io/github/last-commit/wiiplayer2/obs-scripts.svg?style=flat-square)](https://github.com/WiiPlayer2/obs-scripts/commits)\n[![GitHub commit activity the past week, 4 weeks, year](https://img.shields.io/github/commit-activity/4w/WiiPlayer2/obs-scripts.svg?style=flat-square)](https://github.com/WiiPlayer2/obs-scripts/commits)\n\nContains scripts I created for obs-studio (https://github.com/obsproject/obs-studio)\n\n## filter-dropshadow.lua\nThis script adds an effect filter that adds a hard drop shadow to any source it's added to.\n\n## filter-gaussian-blur.lua\nThis script adds an effect filter that blurs a source with a gaussian blur filter.\n\n## filter-custom.lua\nThis script adds a custom effect filter where you can select an effect file yourself.", "updated": "2024-03-19T14:03:33Z", "galleryUrl": "https://community.chocolatey.org/packages/obs-studio-wiiplayer2-scripts/0.4.6657.3109", "abuseUrl": "https://community.chocolatey.org/package/ReportAbuse/obs-studio-wiiplayer2-scripts/0.4.6657.3109", "licenseUrl": "https://github.com/WiiPlayer2/obs-scripts/blob/master/LICENSE", "packageName": "obs-studio-wiiplayer2-scripts", "displayName": "DarkLink's Scripts for OBS Studio", "summary": "DarkLink's Scripts for OBS Studio", "version": "0.4.6657.3109", "icon": "", "author": "WiiPlayer2", "downloadCount": 1122, "tags": ["obs", "scripts", "filter"]}