{"description": "Powershell scripts to convert Puppet YAML reports into different formats (HTML, TeamCity events), and includes a GUI to convert reports on the fly", "updated": "2024-03-22T04:48:27Z", "galleryUrl": "https://community.chocolatey.org/packages/poshpuppetreports/0.9.55", "abuseUrl": "https://community.chocolatey.org/package/ReportAbuse/poshpuppetreports/0.9.55", "licenseUrl": "https://github.com/glennsarti/Puppet-Reports-in-Powershell/blob/master/LICENSE", "packageName": "poshpuppetreports", "displayName": "Posh Puppet Reports", "summary": "", "version": "0.9.55", "icon": "https://raw.githubusercontent.com/glennsarti/Puppet-Reports-in-Powershell/master/resources/poshpuppetreports.png", "author": "Glenn Sarti", "downloadCount": 2617, "tags": ["posh", "powershell", "puppet"]}