{"description": "PsVsts provides a suite of PowerShell functions that help automate interaction with VisualStudio Online. Some of the functions include Push-ToVsts (quickly take a local git repo and host it in a VSTS project), Submit-PullRequest (submits a pull request), Get-Builds and Get-WorkItems.\n\nThis module requires PowersShell version 3 or greater. No explicit dependency is taken to not force a user to upgrade unknowingly.", "updated": "2024-03-17T17:18:35Z", "galleryUrl": "https://community.chocolatey.org/packages/PsVsts/1.0.0", "abuseUrl": "https://community.chocolatey.org/package/ReportAbuse/PsVsts/1.0.0", "licenseUrl": "http://www.apache.org/licenses/LICENSE-2.0.html", "packageName": "PsVsts", "displayName": "PsVsts", "summary": "PsVsts provides a suite of PowerShell functions that help automate interaction with VisualStudio Online.", "version": "1.0.0", "icon": "https://raw.githubusercontent.com/mmanela/PsVsts/master/PsVsts.png", "author": "Matthew Manela", "downloadCount": 1586, "tags": ["powershell", "vso", "vsts", "tfs", "git", "build", "workitem"]}