{"description": "Altap Samalander is a File Manager for Windows. It provides to panes for optimal working with two different file locations. It has a powerful viewer for verious file types included. There are also many plugins for different types of file operations such as checksum calculation and verification, compression and uncompression. It supports to open compressed files (ZIP, 7z) or container files (ISO) in place. - Starting with version 4.0 is freeeware.", "updated": "2024-03-22T12:33:30Z", "galleryUrl": "https://community.chocolatey.org/packages/salamander/4.0.0", "abuseUrl": "https://community.chocolatey.org/package/ReportAbuse/salamander/4.0.0", "licenseUrl": "http://www.altap.cz/salamander/eula/", "packageName": "salamander", "displayName": "Altap Salamander", "summary": "Altap Salamander", "version": "4.0.0", "icon": "https://pbs.twimg.com/profile_images/764156374/altapsalamander_400x400.png", "author": "ALTAP spol. s r.o.", "downloadCount": 1594, "tags": ["salamander", "altap", "windows", "file", "manager", "admin"]}