{"description": "Problem: \"I can manage all my Kubernetes config in git, except Secrets.\"\n\nSolution: Encrypt your Secret into a SealedSecret, which is safe to store - even inside a public repository. The SealedSecret can be decrypted only by the controller running in the target cluster and nobody else (not even the original author) is able to obtain the original Secret from the SealedSecret.", "updated": "2024-03-22T02:03:42Z", "galleryUrl": "https://community.chocolatey.org/packages/sealed-secrets/0.25.0", "abuseUrl": "https://community.chocolatey.org/package/ReportAbuse/sealed-secrets/0.25.0", "licenseUrl": "https://raw.githubusercontent.com/bitnami-labs/sealed-secrets/main/LICENSE", "packageName": "sealed-secrets", "displayName": "Sealed Secrets for Kubernetes", "summary": "A Kubernetes controller and tool for one-way encrypted Secrets", "version": "0.25.0", "icon": "", "author": "Bitnami Labs", "downloadCount": 25, "tags": ["Kubernetes", "k8s", "secrets"]}