{"description": "## The simplest way to try, install, and manage fonts.\n\nInstall fonts from participating sites with a single click. Fonts are installed from the cloud on your computer in seconds.\n\n## Great type should just work.\n**Install and remove fonts from the cloud.**\nNo need to fill up your hard drive. Your fonts are available in the cloud, any time you need them, and you can easily remove fonts when you\u2019re not using them.\n\n**Try fonts in your design apps, before you buy.**\nYou shouldn\u2019t have to spend hard-earned cash to find out if a font is going to work with your content. Font trials work with any desktop application, just like your regularly installed fonts.\n\n**Subscribe to font libraries.**\nOn [participating sites](https://skyfonts.com/#font-providers), subscriptions powered by the SkyFonts service allow \u201call-you-can-eat\u201d access to libraries of over 11,000 fonts.\n\n## Fonts on your computer in seconds.\nWith the SkyFonts app installed on your Windows or Mac OSX system, you simply browse your favorite font websites to find the perfect font, then click the _Install_ button on the site. SkyFonts will download and activate your fonts in seconds.", "updated": "2024-03-18T15:03:25Z", "galleryUrl": "https://community.chocolatey.org/packages/skyfonts/5.9.5.1", "abuseUrl": "https://community.chocolatey.org/package/ReportAbuse/skyfonts/5.9.5.1", "licenseUrl": "https://skyfonts.com/eula/", "packageName": "skyfonts", "displayName": "SkyFonts", "summary": "SkyFonts allows you to install fonts from participating sites such as google fonts and keep them up to date", "version": "5.9.5.1", "icon": "https://cdn.rawgit.com/EntranceJew/chocolatey-packages/1ce2dd155cf4d54d38cbd23bb565d6bfa03f5a41/skyfonts/icon.png", "author": "Monotype Imaging Inc.", "downloadCount": 4374, "tags": ["skyfonts", "font", "manager", "google", "fonts", "cloud", "monotype", "admin"]}