{"description": "Microsoft Kerberos Configuration Manager for SQL Server is a diagnostic tool that helps troubleshoot Kerberos related connectivity issues with SQL Server.", "updated": "2022-07-22T12:30:00Z", "galleryUrl": "https://community.chocolatey.org/packages/SqlKerberosConfigMgr/3.0.0", "abuseUrl": "https://community.chocolatey.org/package/ReportAbuse/SqlKerberosConfigMgr/3.0.0", "licenseUrl": "http://www.microsoft.com/en-us/legal/intellectualproperty/copyright/default.aspx", "packageName": "SqlKerberosConfigMgr", "displayName": "", "summary": "", "version": "3.0.0", "icon": "https://github.com/mwrock/Chocolatey-Packages/raw/master/MsSqlServer2012Express/SqlServer.PNG", "author": "Microsoft", "downloadCount": 2179, "tags": ["SQLServer", "Kerberos"]}