{"description": "Terminals is a secure, multi tab terminal services/remote desktop client. It uses Terminal Services ActiveX Client (mstscax.dll). Supported protocols: Windows remote desktop (RDP), VNC, VMRC. SSH, Telnet, RAS, ICA, Citrix, HTTP and HTTPs based viewers.", "updated": "2024-03-23T23:33:25Z", "galleryUrl": "https://community.chocolatey.org/packages/terminals/4.0.1", "abuseUrl": "https://community.chocolatey.org/package/ReportAbuse/terminals/4.0.1", "licenseUrl": "https://github.com/Terminals-Origin/Terminals/blob/master/LICENSE.md", "packageName": "terminals", "displayName": "Terminals multitab remote control client", "summary": "This is a official Terminals msi installer package.", "version": "4.0.1", "icon": "https://github.com/Terminals-Origin/Terminals/blob/master/Source/Terminals/Resources/terminalsicon.png", "author": "jirkapok rob.chartier", "downloadCount": 387855, "tags": ["terminals", "admin", "ssh", "vnc", "rdp"]}