{"description": "TurnedOnTimesView is a simple tool that analyses the event log of Windows operating system, and detects the time ranges that your computer was turned on.\n\nFor every period of time that the computer was turned on, the following information is displayed: Startup Time, Shutdown Time, Duration, Shutdown Reason, Shutdown Type, Shutdown Process, and Shutdown Code.\n\nTurnedOnTimesView allows you to get this information from your local computer, and from remote computer on your network if you have enough privilege to read the event log of Windows remotely.", "updated": "2024-03-24T00:33:30Z", "galleryUrl": "https://community.chocolatey.org/packages/turnedontimesview/1.46.0", "abuseUrl": "https://community.chocolatey.org/package/ReportAbuse/turnedontimesview/1.46.0", "licenseUrl": "https://www.nirsoft.net/utils/computer_turned_on_times.html", "packageName": "turnedontimesview", "displayName": "TurnedOnTimesView", "summary": "View the time/date ranges that your computer was turned on", "version": "1.46.0", "icon": "https://cdn.jsdelivr.net/gh/TakataSanshiro/Chocolatey-Packages@master/automatic/turnedontimesview/turnedontimesview.png", "author": "Nir Sofer", "downloadCount": 514094, "tags": ["power", "event", "log"]}