{"description": "Visual Subst is a small tool that allows you to associate the most accessed directories with virtual drives", "updated": "2024-03-23T23:33:25Z", "galleryUrl": "https://community.chocolatey.org/packages/visualsubst/1.0.6", "abuseUrl": "https://community.chocolatey.org/package/ReportAbuse/visualsubst/1.0.6", "licenseUrl": "http://www.ntwind.com/privacy.html", "packageName": "visualsubst", "displayName": "Visual Subst", "summary": "Visual Subst is a small tool that allows you to associate the most accessed directories with virtual drives", "version": "1.0.6", "icon": "https://github.com/adorepump/chocolatey-packages/raw/master/visualsubst/visualsubst.png", "author": "ntwing.com team", "downloadCount": 1805, "tags": ["productivity"]}