{"description": "Vitrite is a small Windows utility that allows you to manually adjust the level of transparency for almost any visible window. It does this by utilizing a capability present in Windows for variable window transparency.", "updated": "2024-03-20T13:03:30Z", "galleryUrl": "https://community.chocolatey.org/packages/vitrite/1.1.1", "abuseUrl": "https://community.chocolatey.org/package/ReportAbuse/vitrite/1.1.1", "licenseUrl": "", "packageName": "vitrite", "displayName": "Vitrite", "summary": "Small Windows utility", "version": "1.1.1", "icon": "https://cdn.statically.io/img/vitrite.vanmiddlesworth.org/vitrite/shot-thumb.png", "author": "Ryan VanMiddlesworth", "downloadCount": 329, "tags": ["vitrite", "ontop", "windows", "tool"]}