{"description": "WinSize: Move windows automatically to a predefined place. Resize width and/or height. Moving OR changing size possible. Supports text CONTAINED in titles (like \"Notepad\") to identify window.", "updated": "2024-02-20T00:33:15Z", "galleryUrl": "https://community.chocolatey.org/packages/winsize2/2.38.04", "abuseUrl": "https://community.chocolatey.org/package/ReportAbuse/winsize2/2.38.04", "licenseUrl": "https://www.gnu.org/licenses/old-licenses/gpl-2.0.txt", "packageName": "winsize2", "displayName": "winsize2 (Install)", "summary": "WinSize: Move windows automatically to a predefined place.", "version": "2.38.04", "icon": "https://cdn.jsdelivr.net/gh/corbob/ChocoPackages@master/icons/winsize2.jpg", "author": "magra19", "downloadCount": 429, "tags": ["winsize2"]}