{"description": "Wise Memory Optimizer is a free memory optimization tool. With the exclusive memory defrag technology, it can help you clean up memory, thus making the applications run faster.", "updated": "2024-03-20T22:03:32Z", "galleryUrl": "https://community.chocolatey.org/packages/wizemo/3.51", "abuseUrl": "https://community.chocolatey.org/package/ReportAbuse/wizemo/3.51", "licenseUrl": "", "packageName": "wizemo", "displayName": "Wize Memory Optimizer", "summary": "Easy to defrag memory and free up more memory with one-click.", "version": "3.51", "icon": "https://cdn.rawgit.com/Kristinita/SashaChocolatey/master/icons/Wize-Memory-Optimizer.png", "author": "WiseCleaner.com", "downloadCount": 1089, "tags": ["wize-memory-optimizer", "memory", "memory-optimization", "admin"]}