{"description": "###This packages installs Arch Linux for Windows Subsystem for Linux.\n\t\n**[PACKAGE NOTES](https://github.com/bcurran3/ChocolateyPackages/blob/master/wsl-archlinux/readme.md)**\n\n***\n**Click here to [Patreon-ize](https://www.patreon.com/bcurran3) the package maintainer.**\n***", "updated": "2024-03-24T01:18:29Z", "galleryUrl": "https://community.chocolatey.org/packages/wsl-archlinux/1.0.3.0", "abuseUrl": "https://community.chocolatey.org/package/ReportAbuse/wsl-archlinux/1.0.3.0", "licenseUrl": "https://raw.githubusercontent.com/yuk7/ArchWSL/master/LICENSE", "packageName": "wsl-archlinux", "displayName": "Arch Linux for Windows Subsystem for Linux (Install)", "summary": "This packages installs Arch Linux for Windows Subsystem for Linux.", "version": "1.0.3.0", "icon": "https://www.archlinux.org/static/logos/archlinux-logo-dark-90dpi.ebdee92a15b3.png", "author": "Aaron Griffin,  Allan McRae,  Anatol Pomozov, Andreas Radke,  Andrew Gregory,  Antonio Rojas,  Bart\u0142omiej Piotrowski,  Christian Hesse,  Dan McGee,  Dave Reisner,  Evangelos Foutras,  Felix Yan,  Florian Pritz,  Gaetan Bisson,  Gerardo Pozzi,  Giancarlo Razzolini,  Giovanni Scafora,  Guillaume Alaux,  Ionu\u021b Mircea B\u00eeru,  Jan de Groot,  Jan Steffens,  Jelle van der Waa,  Johannes L\u00f6thberg,  J\u00fcrgen H\u00f6tzel,  Laurent Carlier,  Levente Polyak,  Lukas Fleischer,  Maxime Gauduin,  Pierre Schmitz,  Ray Rashif,  R\u00e9my Oudompheng,  Ronald van Haren,  S\u00e9bastien Luttringer,  Sven-Hendrik Haase,  Thomas B\u00e4chler,  Tobias Powalowski", "downloadCount": 8198, "tags": ["wsl", "arch", "linux"]}